picsnip
