Metadata-Version: 1.0
Name: picsnip
Version: 0.0.3
Summary: Extract illustrations from book page scans
Home-page: https://github.com/yaledhlab/picsnip
Author: Douglas Duhaime
Author-email: douglas.duhaime@gmail.com
License: MIT
Keywords: machine-vision,computer-vision,image-processing,data-collection
Platform: UNKNOWN
